{
  "type": "FeatureCollection",
  "licence": "Data \u00a9 OpenStreetMap contributors, ODbL 1.0. http://osm.org/copyright",
  "features": [
    {
      "type": "Feature",
      "properties": {
        "place_id": 113071589,
        "osm_type": "way",
        "osm_id": 1190381463,
        "place_rank": 30,
        "category": "amenity",
        "type": "kitchen",
        "importance": 7.329747463183058e-05,
        "addresstype": "amenity",
        "name": "105",
        "display_name": "105, Engesserstra\u00dfe, Innenstadt-Ost Nord\u00f6stlicher Teil, Innenstadt-Ost, Karlsruhe, Baden-W\u00fcrttemberg, 76131, Deutschland",
        "address": {
          "amenity": "105",
          "road": "Engesserstra\u00dfe",
          "neighbourhood": "Innenstadt-Ost Nord\u00f6stlicher Teil",
          "suburb": "Innenstadt-Ost",
          "city": "Karlsruhe",
          "state": "Baden-W\u00fcrttemberg",
          "ISO3166-2-lvl4": "DE-BW",
          "postcode": "76131",
          "country": "Deutschland",
          "country_code": "de"
        }
      },
      "bbox": [
        8.4090335,
        49.0122681,
        8.4091157,
        49.0123219
      ],
      "geometry": {
        "type": "Point",
        "coordinates": [
          8.409081535869564,
          49.0122947
        ]
      }
    }
  ]
}
